{"code": 0, "message": "0", "ttl": 1, "data": {"packages": [{"id": 3443, "text": "\u6697\u91d1\u7389\u5154", "url": "https://i0.hdslb.com/bfs/emote/46a66f0f3e57e6cb2330a14a7261e6b9f0326ff4.png", "mtime": 1695182315, "type": 3, "attr": 28, "meta": {"size": 2, "item_id": 59685}, "emote": [{"id": 46972, "package_id": 3443, "text": "[\u6697\u91d1\u7389\u5154_\u4e2d\u79cb\u5feb\u4e50]", "url": "https://i0.hdslb.com/bfs/emote/f90f0aa2a96b754dab8061c2f1e95d7a48233f43.png", "mtime": 1695181214, "type": 3, "attr": 0, "meta": {"size": 2, "suggest": [""], "alias": "\u4e2d\u79cb\u5feb\u4e50"}, "flags": {"no_access": true, "unlocked": false}, "activity": null}, {"id": 46973, "package_id": 3443, "text": "[\u6697\u91d1\u7389\u5154_\u5450]", "url": "https://i0.hdslb.com/bfs/emote/907d65285ee003789f35a8bba588a20ec38870fe.png", "mtime": 1695181406, "type": 3, "attr": 0, "meta": {"size": 2, "suggest": [""], "alias": "\u5450"}, "flags": {"no_access": true, "unlocked": false}, "activity": null}, {"id": 46974, "package_id": 3443, "text": "[\u6697\u91d1\u7389\u5154_\u6ee1\u6708]", "url": "https://i0.hdslb.com/bfs/emote/a0eb270ae3d3f0dc9a4d64999a6e08555f6aafe1.png", "mtime": 1695181406, "type": 3, "attr": 0, "meta": {"size": 2, "suggest": [""], "alias": "\u6ee1\u6708"}, "flags": {"no_access": true, "unlocked": false}, "activity": null}, {"id": 46975, "package_id": 3443, "text": "[\u6697\u91d1\u7389\u5154_\u8d4f\u83ca]", "url": "https://i0.hdslb.com/bfs/emote/2a773a805be706227aced4a7eb6a6bc3c1160263.png", "mtime": 1695181406, "type": 3, "attr": 0, "meta": {"size": 2, "suggest": [""], "alias": "\u8d4f\u83ca"}, "flags": {"no_access": true, "unlocked": false}, "activity": null}, {"id": 46976, "package_id": 3443, "text": "[\u6697\u91d1\u7389\u5154_\u997c\u4f4f\u547c\u5438]", "url": "https://i0.hdslb.com/bfs/emote/a566c0e328a85334544273aa859a24a244add9f1.png", "mtime": 1695181406, "type": 3, "attr": 0, "meta": {"size": 2, "suggest": [""], "alias": "\u997c\u4f4f\u547c\u5438"}, "flags": {"no_access": true, "unlocked": false}, "activity": null}, {"id": 46977, "package_id": 3443, "text": "[\u6697\u91d1\u7389\u5154_\u5466\u5466\u5466]", "url": "https://i0.hdslb.com/bfs/emote/07165b8cea2a8de4916ec8ac56ddd0863d921488.png", "mtime": 1695181598, "type": 3, "attr": 0, "meta": {"size": 2, "suggest": [""], "alias": "\u5466\u5466\u5466"}, "flags": {"no_access": true, "unlocked": false}, "activity": null}, {"id": 46978, "package_id": 3443, "text": "[\u6697\u91d1\u7389\u5154_\u53c8\u6211\uff1f]", "url": "https://i0.hdslb.com/bfs/emote/1892a905f0ba002edc280fabbd7ef4c3b3e6d15b.png", "mtime": 1695181598, "type": 3, "attr": 0, "meta": {"size": 2, "suggest": [""], "alias": "\u53c8\u6211\uff1f"}, "flags": {"no_access": true, "unlocked": false}, "activity": null}, {"id": 46979, "package_id": 3443, "text": "[\u6697\u91d1\u7389\u5154_\u54fc]", "url": "https://i0.hdslb.com/bfs/emote/7d4dfee532ddb48374e9d57b1f97936cebf231af.png", "mtime": 1695181598, "type": 3, "attr": 0, "meta": {"size": 2, "suggest": [""], "alias": "\u54fc"}, "flags": {"no_access": true, "unlocked": false}, "activity": null}, {"id": 46980, "package_id": 3443, "text": "[\u6697\u91d1\u7389\u5154_\u6320\u5934]", "url": "https://i0.hdslb.com/bfs/emote/7fd831ab0380f60084a27cfbf410c5ba2fc98883.png", "mtime": 1695181598, "type": 3, "attr": 0, "meta": {"size": 2, "suggest": [""], "alias": "\u6320\u5934"}, "flags": {"no_access": true, "unlocked": false}, "activity": null}, {"id": 46981, "package_id": 3443, "text": "[\u6697\u91d1\u7389\u5154_\u7231\u4f60]", "url": "https://i0.hdslb.com/bfs/emote/81bb8a102caaa4909a13ef2456bbe7a3e0e100c5.png", "mtime": 1695181598, "type": 3, "attr": 0, "meta": {"size": 2, "suggest": [""], "alias": "\u7231\u4f60"}, "flags": {"no_access": true, "unlocked": false}, "activity": null}, {"id": 46982, "package_id": 3443, "text": "[\u6697\u91d1\u7389\u5154_\u5154\u5154\u5446]", "url": "https://i0.hdslb.com/bfs/emote/e77097a2ea5659a69221b1d68c544177d5d52771.png", "mtime": 1695181887, "type": 3, "attr": 0, "meta": {"size": 2, "suggest": [""], "alias": "\u5154\u5154\u5446"}, "flags": {"no_access": true, "unlocked": false}, "activity": null}, {"id": 46983, "package_id": 3443, "text": "[\u6697\u91d1\u7389\u5154_\u9707\u60ca]", "url": "https://i0.hdslb.com/bfs/emote/4d1a1d9daa40c0f789a3076cb5ebdacf336e292b.png", "mtime": 1695181887, "type": 3, "attr": 0, "meta": {"size": 2, "suggest": [""], "alias": "\u9707\u60ca"}, "flags": {"no_access": true, "unlocked": false}, "activity": null}, {"id": 46984, "package_id": 3443, "text": "[\u6697\u91d1\u7389\u5154_\u4f60\u5c0f\u5b50]", "url": "https://i0.hdslb.com/bfs/emote/585e8e0f2ed811a765aca4e1042b738387a10dc1.png", "mtime": 1695181887, "type": 3, "attr": 0, "meta": {"size": 2, "suggest": [""], "alias": "\u4f60\u5c0f\u5b50"}, "flags": {"no_access": true, "unlocked": false}, "activity": null}, {"id": 46985, "package_id": 3443, "text": "[\u6697\u91d1\u7389\u5154_\u4eb2\u7231\u7684]", "url": "https://i0.hdslb.com/bfs/emote/20bb6b203298a22747f6840bf82ba5dccb1510a0.png", "mtime": 1695181887, "type": 3, "attr": 0, "meta": {"size": 2, "suggest": [""], "alias": "\u4eb2\u7231\u7684"}, "flags": {"no_access": true, "unlocked": false}, "activity": null}, {"id": 46986, "package_id": 3443, "text": "[\u6697\u91d1\u7389\u5154_\u54c7]", "url": "https://i0.hdslb.com/bfs/emote/9cd3eb9402dd45efbb512017793aa9716a97c6dd.png", "mtime": 1695181887, "type": 3, "attr": 0, "meta": {"size": 2, "suggest": [""], "alias": "\u54c7"}, "flags": {"no_access": true, "unlocked": false}, "activity": null}, {"id": 46987, "package_id": 3443, "text": "[\u6697\u91d1\u7389\u5154_\u6295\u964d]", "url": "https://i0.hdslb.com/bfs/emote/05a3345f4bb2bf419ea412a2fc5c624b255b59b3.png", "mtime": 1695181887, "type": 3, "attr": 0, "meta": {"size": 2, "suggest": [""], "alias": "\u6295\u964d"}, "flags": {"no_access": true, "unlocked": false}, "activity": null}, {"id": 46988, "package_id": 3443, "text": "[\u6697\u91d1\u7389\u5154_\u51fa\u6765]", "url": "https://i0.hdslb.com/bfs/emote/013fc7b5b95b33ff63c75d1008daf0d81802ccee.png", "mtime": 1695182060, "type": 3, "attr": 0, "meta": {"size": 2, "suggest": [""], "alias": "\u51fa\u6765"}, "flags": {"no_access": true, "unlocked": false}, "activity": null}, {"id": 46989, "package_id": 3443, "text": "[\u6697\u91d1\u7389\u5154_\u653e\u8fc7\u6211\u5427]", "url": "https://i0.hdslb.com/bfs/emote/7ca06d45758596ceb02ed879e0d17731b869ecd2.png", "mtime": 1695182060, "type": 3, "attr": 0, "meta": {"size": 2, "suggest": [""], "alias": "\u653e\u8fc7\u6211\u5427"}, "flags": {"no_access": true, "unlocked": false}, "activity": null}, {"id": 46990, "package_id": 3443, "text": "[\u6697\u91d1\u7389\u5154_\u7075\u673a\u4e00\u52a8]", "url": "https://i0.hdslb.com/bfs/emote/3299bfd0a63494a72e052ee14019cb5f7aba38f5.png", "mtime": 1695182060, "type": 3, "attr": 0, "meta": {"size": 2, "suggest": [""], "alias": "\u7075\u673a\u4e00\u52a8"}, "flags": {"no_access": true, "unlocked": false}, "activity": null}, {"id": 46991, "package_id": 3443, "text": "[\u6697\u91d1\u7389\u5154_\u6492\u82b1]", "url": "https://i0.hdslb.com/bfs/emote/d9c1d1d09c7f61dda1de5e375f7bbac1d69ef9ae.png", "mtime": 1695182060, "type": 3, "attr": 0, "meta": {"size": 2, "suggest": [""], "alias": "\u6492\u82b1"}, "flags": {"no_access": true, "unlocked": false}, "activity": null}, {"id": 46992, "package_id": 3443, "text": "[\u6697\u91d1\u7389\u5154_\u6655]", "url": "https://i0.hdslb.com/bfs/emote/360c357e46b2c158c51693ab76206502f515dca5.png", "mtime": 1695182315, "type": 3, "attr": 0, "meta": {"size": 2, "suggest": [""], "alias": "\u6655"}, "flags": {"no_access": true, "unlocked": false}, "activity": null}, {"id": 46993, "package_id": 3443, "text": "[\u6697\u91d1\u7389\u5154_\u6b8b\u5ff5]", "url": "https://i0.hdslb.com/bfs/emote/2b2815aa1c10271ab78c8343b572e8ab90887077.png", "mtime": 1695182315, "type": 3, "attr": 0, "meta": {"size": 2, "suggest": [""], "alias": "\u6b8b\u5ff5"}, "flags": {"no_access": true, "unlocked": false}, "activity": null}, {"id": 46994, "package_id": 3443, "text": "[\u6697\u91d1\u7389\u5154_\u4f18\u96c5]", "url": "https://i0.hdslb.com/bfs/emote/5511181c789d641b91e364472fa8ef443627beea.png", "mtime": 1695182315, "type": 3, "attr": 0, "meta": {"size": 2, "suggest": [""], "alias": "\u4f18\u96c5"}, "flags": {"no_access": true, "unlocked": false}, "activity": null}, {"id": 46995, "package_id": 3443, "text": "[\u6697\u91d1\u7389\u5154_\u56de\u5bb6\u4e86]", "url": "https://i0.hdslb.com/bfs/emote/4fd44e1f7119503538096528807d860308ee0e99.png", "mtime": 1695182315, "type": 3, "attr": 0, "meta": {"size": 2, "suggest": [""], "alias": "\u56de\u5bb6\u4e86"}, "flags": {"no_access": true, "unlocked": false}, "activity": null}, {"id": 46996, "package_id": 3443, "text": "[\u6697\u91d1\u7389\u5154_\u6469\u591a\u6469\u591a]", "url": "https://i0.hdslb.com/bfs/emote/0c4d1dbb8499ce142aa0407791f05eaf838ce2a7.png", "mtime": 1695182315, "type": 3, "attr": 0, "meta": {"size": 2, "suggest": [""], "alias": "\u6469\u591a\u6469\u591a"}, "flags": {"no_access": true, "unlocked": false}, "activity": null}], "flags": {"no_access": true}, "label": null, "package_sub_title": "", "ref_mid": 0}]}}