{"code": 0, "message": "0", "ttl": 1, "data": {"packages": [{"id": 9837, "text": "\u6653\u6668\u6851\uff08\u5145\u7535\uff09", "url": "https://i0.hdslb.com/bfs/garb/cae2c5ec2c2faa4db3f2d5cac92b9503365e50e9.png", "mtime": 1780150441, "type": 12, "attr": 28, "meta": {"size": 2, "item_url": "https://www.bilibili.com/h5/upower/index?navhide=1&mid=74679957&prePage=emote"}, "emote": [{"id": 138907, "package_id": 9837, "text": "[UPOWER_74679957_\u54c8\u6c14]", "url": "https://i0.hdslb.com/bfs/garb/76e3a0ee0d2b1bd3b8e8df69370a642bd9e6547a.png", "mtime": 1780150441, "type": 12, "attr": 0, "meta": {"size": 2, "alias": "\u54c8\u6c14"}, "flags": {"no_access": true, "unlocked": false}, "activity": null}, {"id": 138908, "package_id": 9837, "text": "[UPOWER_74679957_\u4e09\u8fde]", "url": "https://i0.hdslb.com/bfs/garb/b2e78f0ed839215719c108b28a2d7a51df715ceb.png", "mtime": 1780150441, "type": 12, "attr": 0, "meta": {"size": 2, "alias": "\u4e09\u8fde"}, "flags": {"no_access": true, "unlocked": false}, "activity": null}, {"id": 138909, "package_id": 9837, "text": "[UPOWER_74679957_\u6c57\u989c]", "url": "https://i0.hdslb.com/bfs/garb/f1c60b44ba5a318a10f7e4e89896542550ca623a.png", "mtime": 1780150441, "type": 12, "attr": 0, "meta": {"size": 2, "alias": "\u6c57\u989c"}, "flags": {"no_access": true, "unlocked": false}, "activity": null}, {"id": 138910, "package_id": 9837, "text": "[UPOWER_74679957_\u6211\u614c\u4e86]", "url": "https://i0.hdslb.com/bfs/garb/6f12ae4a93401ebbd7470c5ec58f4c040776314e.png", "mtime": 1780150441, "type": 12, "attr": 0, "meta": {"size": 2, "alias": "\u6211\u614c\u4e86"}, "flags": {"no_access": true, "unlocked": false}, "activity": null}, {"id": 138911, "package_id": 9837, "text": "[UPOWER_74679957_\u5c31\u8fd9]", "url": "https://i0.hdslb.com/bfs/garb/0eec1dc06e8136a49ad064f3e0f247e2f4ac372c.png", "mtime": 1780150441, "type": 12, "attr": 0, "meta": {"size": 2, "alias": "\u5c31\u8fd9"}, "flags": {"no_access": true, "unlocked": false}, "activity": null}, {"id": 138912, "package_id": 9837, "text": "[UPOWER_74679957_\u7834\u9632\u4e86]", "url": "https://i0.hdslb.com/bfs/garb/430cfb01449ad667ed8551221303655fb06b76e8.png", "mtime": 1780150441, "type": 12, "attr": 0, "meta": {"size": 2, "alias": "\u7834\u9632\u4e86"}, "flags": {"no_access": true, "unlocked": false}, "activity": null}, {"id": 138913, "package_id": 9837, "text": "[UPOWER_74679957_\u7ef7\u4e0d\u4f4f\u4e86]", "url": "https://i0.hdslb.com/bfs/garb/f93e7888df1d402c946f13f581a1a7e627ba5c41.png", "mtime": 1780150441, "type": 12, "attr": 0, "meta": {"size": 2, "alias": "\u7ef7\u4e0d\u4f4f\u4e86"}, "flags": {"no_access": true, "unlocked": false}, "activity": null}, {"id": 138914, "package_id": 9837, "text": "[UPOWER_74679957_\u5509\u563f]", "url": "https://i0.hdslb.com/bfs/garb/ef7d2f900b32c4e8cc481a98c4addd87c1664b13.png", "mtime": 1780150441, "type": 12, "attr": 0, "meta": {"size": 2, "alias": "\u5509\u563f"}, "flags": {"no_access": true, "unlocked": false}, "activity": null}], "flags": {"no_access": true}, "label": {"font_color": "#FFB027", "background_color": "#FFF6E4", "text": "\u5145\u7535"}, "package_sub_title": "", "ref_mid": 74679957, "resource_type": 0}]}}