{"code": 0, "message": "0", "ttl": 1, "data": {"packages": [{"id": 8416, "text": "SUMMER LOVE \u9759\u6001\u8868\u60c5\u5305", "url": "https://i0.hdslb.com/bfs/garb/c4a87031d4017596c17e722d517622c48de6a435.png", "mtime": 1753099201, "type": 3, "attr": 28, "meta": {"size": 2, "item_id": 1752220424001}, "emote": [{"id": 115902, "package_id": 8416, "text": "[SUMMER LOVE \u9759\u6001\u8868\u60c5\u5305_\u4f60\u597d\u5440]", "url": "https://i0.hdslb.com/bfs/garb/ff9464653d78217cb3e7aede8b0949ca79891c72.png", "mtime": 1753099201, "type": 3, "attr": 0, "meta": {"size": 2, "alias": "\u4f60\u597d\u5440"}, "flags": {"no_access": true, "unlocked": false}, "activity": null}, {"id": 115903, "package_id": 8416, "text": "[SUMMER LOVE \u9759\u6001\u8868\u60c5\u5305_\u7981\u6b62\u5185\u5377]", "url": "https://i0.hdslb.com/bfs/garb/5b260602a5532c3cc8baa0512ee01909c04f6b05.png", "mtime": 1753099201, "type": 3, "attr": 0, "meta": {"size": 2, "alias": "\u7981\u6b62\u5185\u5377"}, "flags": {"no_access": true, "unlocked": false}, "activity": null}, {"id": 115904, "package_id": 8416, "text": "[SUMMER LOVE \u9759\u6001\u8868\u60c5\u5305_\u963f\u5b85\u6c34]", "url": "https://i0.hdslb.com/bfs/garb/1e7bd4068bcd70527bf106923ef7ef9f264c61e0.png", "mtime": 1753099201, "type": 3, "attr": 0, "meta": {"size": 2, "alias": "\u963f\u5b85\u6c34"}, "flags": {"no_access": true, "unlocked": false}, "activity": null}, {"id": 115905, "package_id": 8416, "text": "[SUMMER LOVE \u9759\u6001\u8868\u60c5\u5305_\u533f\u540d\u7f51\u53cb]", "url": "https://i0.hdslb.com/bfs/garb/a325d7d45fdf84f69d7ec7465609505a93da9fc0.png", "mtime": 1753099201, "type": 3, "attr": 0, "meta": {"size": 2, "alias": "\u533f\u540d\u7f51\u53cb"}, "flags": {"no_access": true, "unlocked": false}, "activity": null}, {"id": 115906, "package_id": 8416, "text": "[SUMMER LOVE \u9759\u6001\u8868\u60c5\u5305_\u4fdd\u5bc6]", "url": "https://i0.hdslb.com/bfs/garb/2020a1142a15be512b9e206e04db5f6a359bf9ec.png", "mtime": 1753099201, "type": 3, "attr": 0, "meta": {"size": 2, "alias": "\u4fdd\u5bc6"}, "flags": {"no_access": true, "unlocked": false}, "activity": null}, {"id": 115907, "package_id": 8416, "text": "[SUMMER LOVE \u9759\u6001\u8868\u60c5\u5305_\u6f5c\u6c34\u4e2d]", "url": "https://i0.hdslb.com/bfs/garb/6ad274c824b89cf819ed254d9aecf3491421f8f8.png", "mtime": 1753099201, "type": 3, "attr": 0, "meta": {"size": 2, "alias": "\u6f5c\u6c34\u4e2d"}, "flags": {"no_access": true, "unlocked": false}, "activity": null}, {"id": 115908, "package_id": 8416, "text": "[SUMMER LOVE \u9759\u6001\u8868\u60c5\u5305_\u6478\u9c7c\u4e2d]", "url": "https://i0.hdslb.com/bfs/garb/d346cfc0faddb78e776cf4b76b457932913bf9b5.png", "mtime": 1753099201, "type": 3, "attr": 0, "meta": {"size": 2, "alias": "\u6478\u9c7c\u4e2d"}, "flags": {"no_access": true, "unlocked": false}, "activity": null}, {"id": 115909, "package_id": 8416, "text": "[SUMMER LOVE \u9759\u6001\u8868\u60c5\u5305_\u5403\u74dc\u4e2d]", "url": "https://i0.hdslb.com/bfs/garb/9e87bf51c8fa0ff622a742239c36a4bdc9daa137.png", "mtime": 1753099201, "type": 3, "attr": 0, "meta": {"size": 2, "alias": "\u5403\u74dc\u4e2d"}, "flags": {"no_access": true, "unlocked": false}, "activity": null}, {"id": 115910, "package_id": 8416, "text": "[SUMMER LOVE \u9759\u6001\u8868\u60c5\u5305_\u6e38\u620f\u4e2d]", "url": "https://i0.hdslb.com/bfs/garb/3eb2730e57d084ba266b1d1f1616c6d4688be37a.png", "mtime": 1753099201, "type": 3, "attr": 0, "meta": {"size": 2, "alias": "\u6e38\u620f\u4e2d"}, "flags": {"no_access": true, "unlocked": false}, "activity": null}, {"id": 115911, "package_id": 8416, "text": "[SUMMER LOVE \u9759\u6001\u8868\u60c5\u5305_\u6697\u4e2d\u89c2\u5bdf]", "url": "https://i0.hdslb.com/bfs/garb/c521947cb676a4ab78e060aa98273f81b65b844f.png", "mtime": 1753099201, "type": 3, "attr": 0, "meta": {"size": 2, "alias": "\u6697\u4e2d\u89c2\u5bdf"}, "flags": {"no_access": true, "unlocked": false}, "activity": null}, {"id": 115912, "package_id": 8416, "text": "[SUMMER LOVE \u9759\u6001\u8868\u60c5\u5305_\u52aa\u529b\u642c\u7816]", "url": "https://i0.hdslb.com/bfs/garb/22aea0ee7870612f378e4b53199120565d342240.png", "mtime": 1753099201, "type": 3, "attr": 0, "meta": {"size": 2, "alias": "\u52aa\u529b\u642c\u7816"}, "flags": {"no_access": true, "unlocked": false}, "activity": null}, {"id": 115913, "package_id": 8416, "text": "[SUMMER LOVE \u9759\u6001\u8868\u60c5\u5305_\u6211\u9178\u4e86]", "url": "https://i0.hdslb.com/bfs/garb/bb71c48efea86438f030fdfb61840e6432ecb6ef.png", "mtime": 1753099201, "type": 3, "attr": 0, "meta": {"size": 2, "alias": "\u6211\u9178\u4e86"}, "flags": {"no_access": true, "unlocked": false}, "activity": null}, {"id": 115914, "package_id": 8416, "text": "[SUMMER LOVE \u9759\u6001\u8868\u60c5\u5305_\u5fc3\u82b1\u6012\u653e]", "url": "https://i0.hdslb.com/bfs/garb/98ea3176171f5ce16b53e51aff29a256376ec6d9.png", "mtime": 1753099201, "type": 3, "attr": 0, "meta": {"size": 2, "alias": "\u5fc3\u82b1\u6012\u653e"}, "flags": {"no_access": true, "unlocked": false}, "activity": null}, {"id": 115915, "package_id": 8416, "text": "[SUMMER LOVE \u9759\u6001\u8868\u60c5\u5305_\u4e16\u754c\u7b2c\u4e00]", "url": "https://i0.hdslb.com/bfs/garb/b253187b776a02f0d9e43b9cf9f4ffd001a15fe5.png", "mtime": 1753099201, "type": 3, "attr": 0, "meta": {"size": 2, "alias": "\u4e16\u754c\u7b2c\u4e00"}, "flags": {"no_access": true, "unlocked": false}, "activity": null}, {"id": 115916, "package_id": 8416, "text": "[SUMMER LOVE \u9759\u6001\u8868\u60c5\u5305_\u75af\u72c2\u5fc3\u52a8]", "url": "https://i0.hdslb.com/bfs/garb/f2196491d0ad5668101ad31522f537d3fb4296f5.png", "mtime": 1753099201, "type": 3, "attr": 0, "meta": {"size": 2, "alias": "\u75af\u72c2\u5fc3\u52a8"}, "flags": {"no_access": true, "unlocked": false}, "activity": null}, {"id": 115917, "package_id": 8416, "text": "[SUMMER LOVE \u9759\u6001\u8868\u60c5\u5305_YYDS]", "url": "https://i0.hdslb.com/bfs/garb/a447a0918b2735364ca637b95e21a499db0266b2.png", "mtime": 1753099201, "type": 3, "attr": 0, "meta": {"size": 2, "alias": "YYDS"}, "flags": {"no_access": true, "unlocked": false}, "activity": null}, {"id": 115918, "package_id": 8416, "text": "[SUMMER LOVE \u9759\u6001\u8868\u60c5\u5305_\u997f\u997f\u996d\u996d]", "url": "https://i0.hdslb.com/bfs/garb/898cf9a291edc17f4dea860d5e1ac5beeda9d78b.png", "mtime": 1753099201, "type": 3, "attr": 0, "meta": {"size": 2, "alias": "\u997f\u997f\u996d\u996d"}, "flags": {"no_access": true, "unlocked": false}, "activity": null}, {"id": 115919, "package_id": 8416, "text": "[SUMMER LOVE \u9759\u6001\u8868\u60c5\u5305_\u7edd\u4e16\u597d\u996d]", "url": "https://i0.hdslb.com/bfs/garb/2cf2afc6c56637bbc30c700c90cae0a9e0363976.png", "mtime": 1753099201, "type": 3, "attr": 0, "meta": {"size": 2, "alias": "\u7edd\u4e16\u597d\u996d"}, "flags": {"no_access": true, "unlocked": false}, "activity": null}, {"id": 115920, "package_id": 8416, "text": "[SUMMER LOVE \u9759\u6001\u8868\u60c5\u5305_\u5988\u5988\u7231\u4f60]", "url": "https://i0.hdslb.com/bfs/garb/967382df5df332f6c279754fb4d36274ca5fa604.png", "mtime": 1753099201, "type": 3, "attr": 0, "meta": {"size": 2, "alias": "\u5988\u5988\u7231\u4f60"}, "flags": {"no_access": true, "unlocked": false}, "activity": null}, {"id": 115921, "package_id": 8416, "text": "[SUMMER LOVE \u9759\u6001\u8868\u60c5\u5305_\u5927\u5403\u7279\u5403]", "url": "https://i0.hdslb.com/bfs/garb/0b87c1795f3ea7b15bd39a8dd9321760d5d4e0da.png", "mtime": 1753099201, "type": 3, "attr": 0, "meta": {"size": 2, "alias": "\u5927\u5403\u7279\u5403"}, "flags": {"no_access": true, "unlocked": false}, "activity": null}, {"id": 115922, "package_id": 8416, "text": "[SUMMER LOVE \u9759\u6001\u8868\u60c5\u5305_\u88c5\u50bb]", "url": "https://i0.hdslb.com/bfs/garb/31e4521ba9a68c0c79a9de35a5d2c48d2cff1768.png", "mtime": 1753099201, "type": 3, "attr": 0, "meta": {"size": 2, "alias": "\u88c5\u50bb"}, "flags": {"no_access": true, "unlocked": false}, "activity": null}, {"id": 115923, "package_id": 8416, "text": "[SUMMER LOVE \u9759\u6001\u8868\u60c5\u5305_\u88c5\u9177]", "url": "https://i0.hdslb.com/bfs/garb/9a687c76257c524aec936bcd99295a2d251b2eeb.png", "mtime": 1753099201, "type": 3, "attr": 0, "meta": {"size": 2, "alias": "\u88c5\u9177"}, "flags": {"no_access": true, "unlocked": false}, "activity": null}, {"id": 115924, "package_id": 8416, "text": "[SUMMER LOVE \u9759\u6001\u8868\u60c5\u5305_\u671f\u5f85]", "url": "https://i0.hdslb.com/bfs/garb/aeae46276ef0f09ab8e9b591834284e7396fdd41.png", "mtime": 1753099201, "type": 3, "attr": 0, "meta": {"size": 2, "alias": "\u671f\u5f85"}, "flags": {"no_access": true, "unlocked": false}, "activity": null}, {"id": 115925, "package_id": 8416, "text": "[SUMMER LOVE \u9759\u6001\u8868\u60c5\u5305_\u6478\u6478\u5934]", "url": "https://i0.hdslb.com/bfs/garb/f2273d5f2e8858edc8341bf1a37a7a7af58a700c.png", "mtime": 1753099201, "type": 3, "attr": 0, "meta": {"size": 2, "alias": "\u6478\u6478\u5934"}, "flags": {"no_access": true, "unlocked": false}, "activity": null}, {"id": 115926, "package_id": 8416, "text": "[SUMMER LOVE \u9759\u6001\u8868\u60c5\u5305_\u597d\u8036]", "url": "https://i0.hdslb.com/bfs/garb/2f59e028c83fca59778603e3a3897986bcde874d.png", "mtime": 1753099201, "type": 3, "attr": 0, "meta": {"size": 2, "alias": "\u597d\u8036"}, "flags": {"no_access": true, "unlocked": false}, "activity": null}], "flags": {"no_access": true}, "label": null, "package_sub_title": "", "ref_mid": 0, "resource_type": 0}]}}