{"code": 0, "message": "0", "ttl": 1, "data": {"packages": [{"id": 10115, "text": "\u516d\u4e8c\u4e8c\u8868\u60c5\u5305", "url": "https://i0.hdslb.com/bfs/garb/item/2f0f092f0a05ce710f80fa96f16320d72556f151.png", "mtime": 1784529449, "type": 3, "attr": 28, "meta": {"size": 2, "item_id": 1784278138001}, "emote": [{"id": 143748, "package_id": 10115, "text": "[\u516d\u4e8c\u4e8c\u8868\u60c5\u5305_\u592a\u68d2\u5566]", "url": "https://i0.hdslb.com/bfs/garb/item/2c390dc55602d2c1de782fd219d40289841b1961.png", "mtime": 1784529413, "type": 3, "attr": 0, "meta": {"size": 2, "alias": "\u592a\u68d2\u5566"}, "flags": {"no_access": true, "unlocked": false}, "activity": null}, {"id": 143749, "package_id": 10115, "text": "[\u516d\u4e8c\u4e8c\u8868\u60c5\u5305_\u4e00\u952e\u4e09\u8fde]", "url": "https://i0.hdslb.com/bfs/garb/item/fbebb80a53ee193930358ad68f768acf988e4ef3.png", "mtime": 1784529413, "type": 3, "attr": 0, "meta": {"size": 2, "alias": "\u4e00\u952e\u4e09\u8fde"}, "flags": {"no_access": true, "unlocked": false}, "activity": null}, {"id": 143750, "package_id": 10115, "text": "[\u516d\u4e8c\u4e8c\u8868\u60c5\u5305_\u7231\u4f60]", "url": "https://i0.hdslb.com/bfs/garb/item/141913952bde7690601214b27252f9e25114e72b.png", "mtime": 1784529413, "type": 3, "attr": 0, "meta": {"size": 2, "alias": "\u7231\u4f60"}, "flags": {"no_access": true, "unlocked": false}, "activity": null}, {"id": 143751, "package_id": 10115, "text": "[\u516d\u4e8c\u4e8c\u8868\u60c5\u5305_\u54c8\u54c8\u54c8]", "url": "https://i0.hdslb.com/bfs/garb/item/d89619bcc5ce827583e3c0abb95a06e4a378f351.png", "mtime": 1784529413, "type": 3, "attr": 0, "meta": {"size": 2, "alias": "\u54c8\u54c8\u54c8"}, "flags": {"no_access": true, "unlocked": false}, "activity": null}, {"id": 143752, "package_id": 10115, "text": "[\u516d\u4e8c\u4e8c\u8868\u60c5\u5305_\u8981\u8d34\u8d34]", "url": "https://i0.hdslb.com/bfs/garb/item/b656fb443c71272ba7cfbdb930073796f2959388.png", "mtime": 1784529413, "type": 3, "attr": 0, "meta": {"size": 2, "alias": "\u8981\u8d34\u8d34"}, "flags": {"no_access": true, "unlocked": false}, "activity": null}, {"id": 143753, "package_id": 10115, "text": "[\u516d\u4e8c\u4e8c\u8868\u60c5\u5305_\u4ffa\u6765\u4e86]", "url": "https://i0.hdslb.com/bfs/garb/item/5bac266d2b5a55d51d11d28e3636f22ca8567a36.png", "mtime": 1784529413, "type": 3, "attr": 0, "meta": {"size": 2, "alias": "\u4ffa\u6765\u4e86"}, "flags": {"no_access": true, "unlocked": false}, "activity": null}, {"id": 143754, "package_id": 10115, "text": "[\u516d\u4e8c\u4e8c\u8868\u60c5\u5305_\u6563\u53d1\u9b45\u529b]", "url": "https://i0.hdslb.com/bfs/garb/item/1f206563fce9c957e268745ee163a86399c319b5.png", "mtime": 1784529413, "type": 3, "attr": 0, "meta": {"size": 2, "alias": "\u6563\u53d1\u9b45\u529b"}, "flags": {"no_access": true, "unlocked": false}, "activity": null}, {"id": 143755, "package_id": 10115, "text": "[\u516d\u4e8c\u4e8c\u8868\u60c5\u5305_missu]", "url": "https://i0.hdslb.com/bfs/garb/item/93c3d6f4706a84a924c658564b0cb83e0c7810e3.png", "mtime": 1784529413, "type": 3, "attr": 0, "meta": {"size": 2, "alias": "missu"}, "flags": {"no_access": true, "unlocked": false}, "activity": null}, {"id": 143756, "package_id": 10115, "text": "[\u516d\u4e8c\u4e8c\u8868\u60c5\u5305_\u53ef\u7231\u554a\uff01]", "url": "https://i0.hdslb.com/bfs/garb/item/0d86086a2ff817c60a480894cd7c64a9bfcfdb52.png", "mtime": 1784529413, "type": 3, "attr": 0, "meta": {"size": 2, "alias": "\u53ef\u7231\u554a\uff01"}, "flags": {"no_access": true, "unlocked": false}, "activity": null}, {"id": 143757, "package_id": 10115, "text": "[\u516d\u4e8c\u4e8c\u8868\u60c5\u5305_\u554a\uff01]", "url": "https://i0.hdslb.com/bfs/garb/item/49b51499704c2e04ad1b0798a64c5f9ec8fb63c8.png", "mtime": 1784529413, "type": 3, "attr": 0, "meta": {"size": 2, "alias": "\u554a\uff01"}, "flags": {"no_access": true, "unlocked": false}, "activity": null}], "flags": {"no_access": true}, "label": null, "package_sub_title": "", "ref_mid": 0, "resource_type": 0}]}}