{"code": 0, "message": "0", "ttl": 1, "data": {"packages": [{"id": 3338, "text": "\u6253call", "url": "https://i0.hdslb.com/bfs/garb/f52f5bb61147017fc8f7787a1202490ce9603ca9.png", "mtime": 1693836000, "type": 3, "attr": 28, "meta": {"size": 2, "item_id": 1692607065001}, "emote": [{"id": 45208, "package_id": 3338, "text": "[\u6253call_\u6253call01]", "url": "https://i0.hdslb.com/bfs/garb/6421ec08299fa06e48cb754227cd5bbe814e6e5e.png", "mtime": 1693836000, "type": 3, "attr": 0, "meta": {"size": 2, "alias": "\u6253call01"}, "flags": {"no_access": true, "unlocked": false}, "activity": null}, {"id": 45209, "package_id": 3338, "text": "[\u6253call_\u6253call02]", "url": "https://i0.hdslb.com/bfs/garb/e15f43118365da4a178e89f6d50ce3394cf358b7.png", "mtime": 1693836000, "type": 3, "attr": 0, "meta": {"size": 2, "alias": "\u6253call02"}, "flags": {"no_access": true, "unlocked": false}, "activity": null}, {"id": 45210, "package_id": 3338, "text": "[\u6253call_\u6253call03]", "url": "https://i0.hdslb.com/bfs/garb/9772e41e7d958c0edce88de3c2c92547717104f2.png", "mtime": 1693836000, "type": 3, "attr": 0, "meta": {"size": 2, "alias": "\u6253call03"}, "flags": {"no_access": true, "unlocked": false}, "activity": null}, {"id": 45211, "package_id": 3338, "text": "[\u6253call_\u6253call04]", "url": "https://i0.hdslb.com/bfs/garb/162d676302c22699ed7af63b6f17f0a3ac1529ba.png", "mtime": 1693836000, "type": 3, "attr": 0, "meta": {"size": 2, "alias": "\u6253call04"}, "flags": {"no_access": true, "unlocked": false}, "activity": null}, {"id": 45212, "package_id": 3338, "text": "[\u6253call_\u6253call05]", "url": "https://i0.hdslb.com/bfs/garb/0cf289a34cfcd322bdcba551879f394c88676dbc.png", "mtime": 1693836000, "type": 3, "attr": 0, "meta": {"size": 2, "alias": "\u6253call05"}, "flags": {"no_access": true, "unlocked": false}, "activity": null}, {"id": 45213, "package_id": 3338, "text": "[\u6253call_\u6253call06]", "url": "https://i0.hdslb.com/bfs/garb/bb56e3dc458fe9c140688c783da526ec6949953c.png", "mtime": 1693836000, "type": 3, "attr": 0, "meta": {"size": 2, "alias": "\u6253call06"}, "flags": {"no_access": true, "unlocked": false}, "activity": null}, {"id": 45214, "package_id": 3338, "text": "[\u6253call_\u6253call07]", "url": "https://i0.hdslb.com/bfs/garb/c9c711c8e35410b62e34e49111b07789a79b7f93.png", "mtime": 1693836000, "type": 3, "attr": 0, "meta": {"size": 2, "alias": "\u6253call07"}, "flags": {"no_access": true, "unlocked": false}, "activity": null}, {"id": 45215, "package_id": 3338, "text": "[\u6253call_\u6253call08]", "url": "https://i0.hdslb.com/bfs/garb/2c1212f85f9b3080419a70331bf097faaeeb255b.png", "mtime": 1693836000, "type": 3, "attr": 0, "meta": {"size": 2, "alias": "\u6253call08"}, "flags": {"no_access": true, "unlocked": false}, "activity": null}, {"id": 45216, "package_id": 3338, "text": "[\u6253call_\u6253call09]", "url": "https://i0.hdslb.com/bfs/garb/e97d4cea6ee94ca0326541917d236f41e266e61e.png", "mtime": 1693836000, "type": 3, "attr": 0, "meta": {"size": 2, "alias": "\u6253call09"}, "flags": {"no_access": true, "unlocked": false}, "activity": null}, {"id": 45217, "package_id": 3338, "text": "[\u6253call_\u6253call10]", "url": "https://i0.hdslb.com/bfs/garb/1bd1d2d902f8c066cbf1ea94cd609599478e961e.png", "mtime": 1693836000, "type": 3, "attr": 0, "meta": {"size": 2, "alias": "\u6253call10"}, "flags": {"no_access": true, "unlocked": false}, "activity": null}, {"id": 45218, "package_id": 3338, "text": "[\u6253call_\u6253call11]", "url": "https://i0.hdslb.com/bfs/garb/cf64a16105612db0f12322999d87889bc30ab4c3.png", "mtime": 1693836000, "type": 3, "attr": 0, "meta": {"size": 2, "alias": "\u6253call11"}, "flags": {"no_access": true, "unlocked": false}, "activity": null}, {"id": 45219, "package_id": 3338, "text": "[\u6253call_\u6253call12]", "url": "https://i0.hdslb.com/bfs/garb/07f1b3dd11891b5256c6cd7b04a6c844c221783e.png", "mtime": 1693836000, "type": 3, "attr": 0, "meta": {"size": 2, "alias": "\u6253call12"}, "flags": {"no_access": true, "unlocked": false}, "activity": null}, {"id": 45220, "package_id": 3338, "text": "[\u6253call_\u6253call13]", "url": "https://i0.hdslb.com/bfs/garb/8516c1e49b9fc203d811bd721faf103837b3b435.png", "mtime": 1693836000, "type": 3, "attr": 0, "meta": {"size": 2, "alias": "\u6253call13"}, "flags": {"no_access": true, "unlocked": false}, "activity": null}, {"id": 45221, "package_id": 3338, "text": "[\u6253call_\u6253call14]", "url": "https://i0.hdslb.com/bfs/garb/1361bbe946311a5ea9f725c1a04db65f4a32969e.png", "mtime": 1693836000, "type": 3, "attr": 0, "meta": {"size": 2, "alias": "\u6253call14"}, "flags": {"no_access": true, "unlocked": false}, "activity": null}, {"id": 45222, "package_id": 3338, "text": "[\u6253call_\u6253call15]", "url": "https://i0.hdslb.com/bfs/garb/cd8820bcf7ea6ff04c92311de9f3d45f895cb189.png", "mtime": 1693836000, "type": 3, "attr": 0, "meta": {"size": 2, "alias": "\u6253call15"}, "flags": {"no_access": true, "unlocked": false}, "activity": null}], "flags": {"no_access": true}, "label": null, "package_sub_title": "", "ref_mid": 0}]}}