{"code": 0, "message": "0", "ttl": 1, "data": {"packages": [{"id": 2293, "text": "\u54ac\u54ac\u4eca\u5929\u662f\u9b54\u6cd5\u72d0", "url": "https://i0.hdslb.com/bfs/garb/1b20be23c9ba6fc1a3dbe799716a4be443adbf41.png", "mtime": 1691308800, "type": 3, "attr": 28, "meta": {"size": 2, "item_id": 1690939384001}, "emote": [{"id": 40128, "package_id": 2293, "text": "[\u54ac\u54ac\u4eca\u5929\u662f\u9b54\u6cd5\u72d0_\u62b1\u62b1]", "url": "https://i0.hdslb.com/bfs/garb/fb6139b263feb839dc433ce23d2337b64a4c0540.png", "mtime": 1691308800, "type": 3, "attr": 0, "meta": {"size": 2, "alias": "\u62b1\u62b1"}, "flags": {"no_access": true, "unlocked": false}, "activity": null}, {"id": 40129, "package_id": 2293, "text": "[\u54ac\u54ac\u4eca\u5929\u662f\u9b54\u6cd5\u72d0_\u545c\u545c]", "url": "https://i0.hdslb.com/bfs/garb/a3565fd3165ba9cb61fbf59635e8f5074edaa878.png", "mtime": 1691308800, "type": 3, "attr": 0, "meta": {"size": 2, "alias": "\u545c\u545c"}, "flags": {"no_access": true, "unlocked": false}, "activity": null}, {"id": 40130, "package_id": 2293, "text": "[\u54ac\u54ac\u4eca\u5929\u662f\u9b54\u6cd5\u72d0_\u8ba9\u6211\u5eb7\u5eb7]", "url": "https://i0.hdslb.com/bfs/garb/6f7c32f884484f820bdcf35129fa68719d34ac3f.png", "mtime": 1691308800, "type": 3, "attr": 0, "meta": {"size": 2, "alias": "\u8ba9\u6211\u5eb7\u5eb7"}, "flags": {"no_access": true, "unlocked": false}, "activity": null}, {"id": 40131, "package_id": 2293, "text": "[\u54ac\u54ac\u4eca\u5929\u662f\u9b54\u6cd5\u72d0_\u51b2\u9e2d]", "url": "https://i0.hdslb.com/bfs/garb/2d1bc8506bba1339bd27917cebdc42a90a7c0bac.png", "mtime": 1691308800, "type": 3, "attr": 0, "meta": {"size": 2, "alias": "\u51b2\u9e2d"}, "flags": {"no_access": true, "unlocked": false}, "activity": null}, {"id": 40132, "package_id": 2293, "text": "[\u54ac\u54ac\u4eca\u5929\u662f\u9b54\u6cd5\u72d0_\u7231\u4f60\u54df]", "url": "https://i0.hdslb.com/bfs/garb/a58e1260ce3ca3688d2fe98b37a8df78c0a1c74f.png", "mtime": 1691308800, "type": 3, "attr": 0, "meta": {"size": 2, "alias": "\u7231\u4f60\u54df"}, "flags": {"no_access": true, "unlocked": false}, "activity": null}, {"id": 40133, "package_id": 2293, "text": "[\u54ac\u54ac\u4eca\u5929\u662f\u9b54\u6cd5\u72d0_\u54e5\u54e5]", "url": "https://i0.hdslb.com/bfs/garb/d4a7a4922485e43fabe176e83886e73a2cf2ef04.png", "mtime": 1691308800, "type": 3, "attr": 0, "meta": {"size": 2, "alias": "\u54e5\u54e5"}, "flags": {"no_access": true, "unlocked": false}, "activity": null}, {"id": 40134, "package_id": 2293, "text": "[\u54ac\u54ac\u4eca\u5929\u662f\u9b54\u6cd5\u72d0_emo]", "url": "https://i0.hdslb.com/bfs/garb/00c8a6fe1a017f34f9194c3efa2abb1b0c7fba43.png", "mtime": 1691308800, "type": 3, "attr": 0, "meta": {"size": 2, "alias": "emo"}, "flags": {"no_access": true, "unlocked": false}, "activity": null}, {"id": 40135, "package_id": 2293, "text": "[\u54ac\u54ac\u4eca\u5929\u662f\u9b54\u6cd5\u72d0_\u5632\u7b11]", "url": "https://i0.hdslb.com/bfs/garb/fd6c1193590418bbc1d93a51119c13f3bbec0a57.png", "mtime": 1691308800, "type": 3, "attr": 0, "meta": {"size": 2, "alias": "\u5632\u7b11"}, "flags": {"no_access": true, "unlocked": false}, "activity": null}, {"id": 40136, "package_id": 2293, "text": "[\u54ac\u54ac\u4eca\u5929\u662f\u9b54\u6cd5\u72d0_\u665a\u5b89]", "url": "https://i0.hdslb.com/bfs/garb/df2d99407a9086b3d52dded9d829fab780a028df.png", "mtime": 1691308800, "type": 3, "attr": 0, "meta": {"size": 2, "alias": "\u665a\u5b89"}, "flags": {"no_access": true, "unlocked": false}, "activity": null}, {"id": 40137, "package_id": 2293, "text": "[\u54ac\u54ac\u4eca\u5929\u662f\u9b54\u6cd5\u72d0_\u840c\u6df7\u8fc7\u5173]", "url": "https://i0.hdslb.com/bfs/garb/c3344c43375ed3e309196f1c01521f0b1e5358c0.png", "mtime": 1691308800, "type": 3, "attr": 0, "meta": {"size": 2, "alias": "\u840c\u6df7\u8fc7\u5173"}, "flags": {"no_access": true, "unlocked": false}, "activity": null}, {"id": 40138, "package_id": 2293, "text": "[\u54ac\u54ac\u4eca\u5929\u662f\u9b54\u6cd5\u72d0_\u9634\u6697]", "url": "https://i0.hdslb.com/bfs/garb/f8e9fa5bbf71e7b1364088615ccd57e8b2deebf5.png", "mtime": 1691308800, "type": 3, "attr": 0, "meta": {"size": 2, "alias": "\u9634\u6697"}, "flags": {"no_access": true, "unlocked": false}, "activity": null}, {"id": 40139, "package_id": 2293, "text": "[\u54ac\u54ac\u4eca\u5929\u662f\u9b54\u6cd5\u72d0_\u5938\u5938]", "url": "https://i0.hdslb.com/bfs/garb/21e97ddda446ce080b57e4fc56ae1853f030b6db.png", "mtime": 1691308800, "type": 3, "attr": 0, "meta": {"size": 2, "alias": "\u5938\u5938"}, "flags": {"no_access": true, "unlocked": false}, "activity": null}, {"id": 40140, "package_id": 2293, "text": "[\u54ac\u54ac\u4eca\u5929\u662f\u9b54\u6cd5\u72d0_\u5feb\u4e50]", "url": "https://i0.hdslb.com/bfs/garb/1a835ebf62d73a76cad1d5c2bdba7021f5b8c716.png", "mtime": 1691308800, "type": 3, "attr": 0, "meta": {"size": 2, "alias": "\u5feb\u4e50"}, "flags": {"no_access": true, "unlocked": false}, "activity": null}, {"id": 40141, "package_id": 2293, "text": "[\u54ac\u54ac\u4eca\u5929\u662f\u9b54\u6cd5\u72d0_\u6ca1\u6551\u4e86]", "url": "https://i0.hdslb.com/bfs/garb/a7e3dd53f19f628696157d692c7b2addc113f4e4.png", "mtime": 1691308800, "type": 3, "attr": 0, "meta": {"size": 2, "alias": "\u6ca1\u6551\u4e86"}, "flags": {"no_access": true, "unlocked": false}, "activity": null}, {"id": 40142, "package_id": 2293, "text": "[\u54ac\u54ac\u4eca\u5929\u662f\u9b54\u6cd5\u72d0_\u6211\u8db4\u4e86]", "url": "https://i0.hdslb.com/bfs/garb/a47e7ef00a3e770b43803513f0d030c1ec1f3ebd.png", "mtime": 1691308800, "type": 3, "attr": 0, "meta": {"size": 2, "alias": "\u6211\u8db4\u4e86"}, "flags": {"no_access": true, "unlocked": false}, "activity": null}], "flags": {"no_access": true}, "label": null, "package_sub_title": "", "ref_mid": 0}]}}