{"code":0,"message":"0","ttl":1,"data":{"packages":[{"id":585,"text":"籽岷","url":"http://i0.hdslb.com/bfs/garb/00d7c7295058bba8d09881687e2d329937e1eaa6.png","mtime":1668480500,"type":12,"attr":28,"meta":{"size":2},"emote":[{"id":10619,"package_id":585,"text":"[UPOWER_686127_二次元]","url":"http://i0.hdslb.com/bfs/garb/d0d553c08b45765a30324b14e325f8c796860f76.png","mtime":1668480500,"type":12,"attr":0,"meta":{"size":2,"alias":"二次元"},"flags":{"no_access":true,"unlocked":false},"activity":null},{"id":10620,"package_id":585,"text":"[UPOWER_686127_What]","url":"http://i0.hdslb.com/bfs/garb/190c6a09aa046c527fcdfc82e642e2061c5f65f8.png","mtime":1668480500,"type":12,"attr":0,"meta":{"size":2,"alias":"What"},"flags":{"no_access":true,"unlocked":false},"activity":null},{"id":10621,"package_id":585,"text":"[UPOWER_686127_方头方脑]","url":"http://i0.hdslb.com/bfs/garb/38ddf179f0a338d70ad94aab57df359f68157ac9.png","mtime":1668480500,"type":12,"attr":0,"meta":{"size":2,"alias":"方头方脑"},"flags":{"no_access":true,"unlocked":false},"activity":null},{"id":10622,"package_id":585,"text":"[UPOWER_686127_开怀大笑]","url":"http://i0.hdslb.com/bfs/garb/98fb9f1128c6846533f170dc866b5677c2603884.png","mtime":1668480500,"type":12,"attr":0,"meta":{"size":2,"alias":"开怀大笑"},"flags":{"no_access":true,"unlocked":false},"activity":null},{"id":10623,"package_id":585,"text":"[UPOWER_686127_闪亮登场]","url":"http://i0.hdslb.com/bfs/garb/f855133d0e0417472c35e13ca729f99ed578657f.png","mtime":1668480500,"type":12,"attr":0,"meta":{"size":2,"alias":"闪亮登场"},"flags":{"no_access":true,"unlocked":false},"activity":null},{"id":10624,"package_id":585,"text":"[UPOWER_686127_实力]","url":"http://i0.hdslb.com/bfs/garb/26bc3cc0fa5ca4961eaf7d78a15b7038c6908c3a.png","mtime":1668480500,"type":12,"attr":0,"meta":{"size":2,"alias":"实力"},"flags":{"no_access":true,"unlocked":false},"activity":null},{"id":10625,"package_id":585,"text":"[UPOWER_686127_头大]","url":"http://i0.hdslb.com/bfs/garb/64c50aaa91164fda9e4ee6f331dc303dbb2b518b.png","mtime":1668480500,"type":12,"attr":0,"meta":{"size":2,"alias":"头大"},"flags":{"no_access":true,"unlocked":false},"activity":null},{"id":10626,"package_id":585,"text":"[UPOWER_686127_我的神镐]","url":"http://i0.hdslb.com/bfs/garb/67c86aa5f1a893562647a963ffca28241f98d5da.png","mtime":1668480500,"type":12,"attr":0,"meta":{"size":2,"alias":"我的神镐"},"flags":{"no_access":true,"unlocked":false},"activity":null},{"id":10627,"package_id":585,"text":"[UPOWER_686127_心痛]","url":"http://i0.hdslb.com/bfs/garb/f284fc9fae595e8106683454576913cc8ee6de53.png","mtime":1668480500,"type":12,"attr":0,"meta":{"size":2,"alias":"心痛"},"flags":{"no_access":true,"unlocked":false},"activity":null},{"id":10628,"package_id":585,"text":"[UPOWER_686127_真男人]","url":"http://i0.hdslb.com/bfs/garb/a2e2280180752ac755ccddd28aa373ea30881c7e.png","mtime":1668480500,"type":12,"attr":0,"meta":{"size":2,"alias":"真男人"},"flags":{"no_access":true,"unlocked":false},"activity":null}],"flags":{"no_access":true},"label":{"font_color":"#FFB027","background_color":"#FFF6E4","text":"充电"},"package_sub_title":"","ref_mid":686127}]}}
