{"code": 0, "message": "0", "ttl": 1, "data": {"packages": [{"id": 8750, "text": "\u5377\u5377\u732b \u79cd\u83dc\u5427", "url": "https://i0.hdslb.com/bfs/garb/bbb3d312e5a048ba17ae37fe703319b3b21b9752.png", "mtime": 1758512571, "type": 3, "attr": 28, "meta": {"size": 2, "item_id": 1758120794001}, "emote": [{"id": 121453, "package_id": 8750, "text": "[\u5377\u5377\u732b \u79cd\u83dc\u5427_\u571f\u8c46]", "url": "https://i0.hdslb.com/bfs/garb/21e04336395bd10c382942d14fb4aee182b011cd.png", "mtime": 1758512571, "type": 3, "attr": 0, "meta": {"size": 2, "alias": "\u571f\u8c46"}, "flags": {"no_access": true, "unlocked": false}, "activity": null}, {"id": 121454, "package_id": 8750, "text": "[\u5377\u5377\u732b \u79cd\u83dc\u5427_\u5357\u74dc]", "url": "https://i0.hdslb.com/bfs/garb/14e9e0ab393e6aa83383151540999ad65a8c3a51.png", "mtime": 1758512571, "type": 3, "attr": 0, "meta": {"size": 2, "alias": "\u5357\u74dc"}, "flags": {"no_access": true, "unlocked": false}, "activity": null}, {"id": 121455, "package_id": 8750, "text": "[\u5377\u5377\u732b \u79cd\u83dc\u5427_\u5927\u767d\u83dc]", "url": "https://i0.hdslb.com/bfs/garb/15bcce7ec8043f68a14e11fe71282d0e25d7188b.png", "mtime": 1758512571, "type": 3, "attr": 0, "meta": {"size": 2, "alias": "\u5927\u767d\u83dc"}, "flags": {"no_access": true, "unlocked": false}, "activity": null}, {"id": 121456, "package_id": 8750, "text": "[\u5377\u5377\u732b \u79cd\u83dc\u5427_\u5927\u849c]", "url": "https://i0.hdslb.com/bfs/garb/c8ea17b4c6601c83d34f4ef266c23756a7ac8cfc.png", "mtime": 1758512571, "type": 3, "attr": 0, "meta": {"size": 2, "alias": "\u5927\u849c"}, "flags": {"no_access": true, "unlocked": false}, "activity": null}, {"id": 121457, "package_id": 8750, "text": "[\u5377\u5377\u732b \u79cd\u83dc\u5427_\u7389\u7c73]", "url": "https://i0.hdslb.com/bfs/garb/f0b8e5da60277877518812da28df6fc48522c6cb.png", "mtime": 1758512571, "type": 3, "attr": 0, "meta": {"size": 2, "alias": "\u7389\u7c73"}, "flags": {"no_access": true, "unlocked": false}, "activity": null}, {"id": 121458, "package_id": 8750, "text": "[\u5377\u5377\u732b \u79cd\u83dc\u5427_\u5927\u8471]", "url": "https://i0.hdslb.com/bfs/garb/1178870455737bbc87bcc51799a553d20c16094c.png", "mtime": 1758512571, "type": 3, "attr": 0, "meta": {"size": 2, "alias": "\u5927\u8471"}, "flags": {"no_access": true, "unlocked": false}, "activity": null}, {"id": 121459, "package_id": 8750, "text": "[\u5377\u5377\u732b \u79cd\u83dc\u5427_\u563b\u563b]", "url": "https://i0.hdslb.com/bfs/garb/d9e2a0a8f3ef7e5668eb0d53edb977e75ccdf13f.png", "mtime": 1758512571, "type": 3, "attr": 0, "meta": {"size": 2, "alias": "\u563b\u563b"}, "flags": {"no_access": true, "unlocked": false}, "activity": null}, {"id": 121460, "package_id": 8750, "text": "[\u5377\u5377\u732b \u79cd\u83dc\u5427_\u751f\u6c14]", "url": "https://i0.hdslb.com/bfs/garb/d62ca16bde58a57db260011c215c22950e3fc8d1.png", "mtime": 1758512571, "type": 3, "attr": 0, "meta": {"size": 2, "alias": "\u751f\u6c14"}, "flags": {"no_access": true, "unlocked": false}, "activity": null}, {"id": 121461, "package_id": 8750, "text": "[\u5377\u5377\u732b \u79cd\u83dc\u5427_\u80e1\u841d\u535c]", "url": "https://i0.hdslb.com/bfs/garb/70d7602afe0f0a133248ebac251014e3e48015cd.png", "mtime": 1758512571, "type": 3, "attr": 0, "meta": {"size": 2, "alias": "\u80e1\u841d\u535c"}, "flags": {"no_access": true, "unlocked": false}, "activity": null}, {"id": 121462, "package_id": 8750, "text": "[\u5377\u5377\u732b \u79cd\u83dc\u5427_\u82b1\u82b1]", "url": "https://i0.hdslb.com/bfs/garb/e3a2f41e24bce4481804533267aab3cd44f233cc.png", "mtime": 1758512571, "type": 3, "attr": 0, "meta": {"size": 2, "alias": "\u82b1\u82b1"}, "flags": {"no_access": true, "unlocked": false}, "activity": null}, {"id": 121463, "package_id": 8750, "text": "[\u5377\u5377\u732b \u79cd\u83dc\u5427_\u7ea2\u85af]", "url": "https://i0.hdslb.com/bfs/garb/96fb124fe3fdb3fe5121eb91f9774ecb41a6449d.png", "mtime": 1758512571, "type": 3, "attr": 0, "meta": {"size": 2, "alias": "\u7ea2\u85af"}, "flags": {"no_access": true, "unlocked": false}, "activity": null}, {"id": 121464, "package_id": 8750, "text": "[\u5377\u5377\u732b \u79cd\u83dc\u5427_\u5c0f\u82e6\u74dc]", "url": "https://i0.hdslb.com/bfs/garb/1c2cbd1e2bf62b3b99bd645ad3acbda7f1952b3a.png", "mtime": 1758512571, "type": 3, "attr": 0, "meta": {"size": 2, "alias": "\u5c0f\u82e6\u74dc"}, "flags": {"no_access": true, "unlocked": false}, "activity": null}, {"id": 121465, "package_id": 8750, "text": "[\u5377\u5377\u732b \u79cd\u83dc\u5427_\u54c8\u54c8]", "url": "https://i0.hdslb.com/bfs/garb/9cf151c6dd07de11caa38c378cdcb185b20ce61e.png", "mtime": 1758512571, "type": 3, "attr": 0, "meta": {"size": 2, "alias": "\u54c8\u54c8"}, "flags": {"no_access": true, "unlocked": false}, "activity": null}, {"id": 121466, "package_id": 8750, "text": "[\u5377\u5377\u732b \u79cd\u83dc\u5427_\u8304\u5b50]", "url": "https://i0.hdslb.com/bfs/garb/22443d6e5bceb60afec8b3dc4862e6e7a859db64.png", "mtime": 1758512571, "type": 3, "attr": 0, "meta": {"size": 2, "alias": "\u8304\u5b50"}, "flags": {"no_access": true, "unlocked": false}, "activity": null}, {"id": 121467, "package_id": 8750, "text": "[\u5377\u5377\u732b \u79cd\u83dc\u5427_\u8fa3\u6912]", "url": "https://i0.hdslb.com/bfs/garb/21e32dfbee00f1973e24bb0872aa05b56a355616.png", "mtime": 1758512571, "type": 3, "attr": 0, "meta": {"size": 2, "alias": "\u8fa3\u6912"}, "flags": {"no_access": true, "unlocked": false}, "activity": null}, {"id": 121468, "package_id": 8750, "text": "[\u5377\u5377\u732b \u79cd\u83dc\u5427_\u897f\u7ea2\u67ff]", "url": "https://i0.hdslb.com/bfs/garb/29d2804d17d3841dd48af864713562741c615ae5.png", "mtime": 1758512571, "type": 3, "attr": 0, "meta": {"size": 2, "alias": "\u897f\u7ea2\u67ff"}, "flags": {"no_access": true, "unlocked": false}, "activity": null}, {"id": 121469, "package_id": 8750, "text": "[\u5377\u5377\u732b \u79cd\u83dc\u5427_\u8c03\u76ae]", "url": "https://i0.hdslb.com/bfs/garb/72e7ddc80837f27972a98751088c381b0d4fc3a7.png", "mtime": 1758512571, "type": 3, "attr": 0, "meta": {"size": 2, "alias": "\u8c03\u76ae"}, "flags": {"no_access": true, "unlocked": false}, "activity": null}, {"id": 121470, "package_id": 8750, "text": "[\u5377\u5377\u732b \u79cd\u83dc\u5427_\u9752\u83dc]", "url": "https://i0.hdslb.com/bfs/garb/93345f5c122730c9edd82883de104c33364ede30.png", "mtime": 1758512571, "type": 3, "attr": 0, "meta": {"size": 2, "alias": "\u9752\u83dc"}, "flags": {"no_access": true, "unlocked": false}, "activity": null}, {"id": 121471, "package_id": 8750, "text": "[\u5377\u5377\u732b \u79cd\u83dc\u5427_\u9ec4\u74dc]", "url": "https://i0.hdslb.com/bfs/garb/bf9bac0d571601147bc54a7d48cd0f75a6b9f5d3.png", "mtime": 1758512571, "type": 3, "attr": 0, "meta": {"size": 2, "alias": "\u9ec4\u74dc"}, "flags": {"no_access": true, "unlocked": false}, "activity": null}, {"id": 121472, "package_id": 8750, "text": "[\u5377\u5377\u732b \u79cd\u83dc\u5427_\u9999\u83c7]", "url": "https://i0.hdslb.com/bfs/garb/137c625408418df597393ff7c2423673c7ca4696.png", "mtime": 1758512571, "type": 3, "attr": 0, "meta": {"size": 2, "alias": "\u9999\u83c7"}, "flags": {"no_access": true, "unlocked": false}, "activity": null}], "flags": {"no_access": true}, "label": null, "package_sub_title": "", "ref_mid": 0, "resource_type": 0}]}}